odoo/addons/pos_order_line_no_unlink/README.rst
odoo/addons/pos_order_line_no_unlink/__init__.py
odoo/addons/pos_order_line_no_unlink/__manifest__.py
odoo/addons/pos_order_line_no_unlink/i18n/fr.po
odoo/addons/pos_order_line_no_unlink/i18n/pos_order_line_no_unlink.pot
odoo/addons/pos_order_line_no_unlink/models/__init__.py
odoo/addons/pos_order_line_no_unlink/models/pos_order_line.py
odoo/addons/pos_order_line_no_unlink/readme/CONTRIBUTORS.rst
odoo/addons/pos_order_line_no_unlink/readme/DESCRIPTION.rst
odoo/addons/pos_order_line_no_unlink/static/description/icon.png
odoo/addons/pos_order_line_no_unlink/static/description/index.html
odoo/addons/pos_order_line_no_unlink/tests/__init__.py
odoo/addons/pos_order_line_no_unlink/tests/test_module.py
odoo12_addon_pos_order_line_no_unlink-12.0.1.0.3.dist-info/METADATA
odoo12_addon_pos_order_line_no_unlink-12.0.1.0.3.dist-info/WHEEL
odoo12_addon_pos_order_line_no_unlink-12.0.1.0.3.dist-info/top_level.txt
odoo12_addon_pos_order_line_no_unlink-12.0.1.0.3.dist-info/RECORD
